{
    "Version": "1.1",
    "Data": {
        "Source": "c:\\users\\diabo\\onedrive\\desktop\\audiotest\\plugins\\wwise\\intermediate\\build\\win64\\unrealgame\\development\\akaudio\\module.akaudio.3_of_9.cpp",
        "ProvidedModule": "",
        "PCH": "c:\\users\\diabo\\onedrive\\desktop\\audiotest\\intermediate\\build\\win64\\audiotest\\development\\engine\\sharedpch.engine.shadowerrors.h.pch",
        "Includes": [
            "c:\\users\\diabo\\onedrive\\desktop\\audiotest\\plugins\\wwise\\intermediate\\build\\win64\\unrealgame\\development\\akaudio\\definitions.akaudio.h",
            "c:\\users\\diabo\\onedrive\\desktop\\audiotest\\plugins\\wwise\\intermediate\\build\\win64\\unrealgame\\inc\\akaudio\\uht\\akgameplaytypes.gen.cpp",
            "c:\\users\\diabo\\onedrive\\desktop\\audiotest\\plugins\\wwise\\source\\akaudio\\classes\\akgameplaytypes.h",
            "c:\\users\\diabo\\onedrive\\desktop\\audiotest\\plugins\\wwise\\source\\akaudio\\classes\\platforms\\akueplatform.h",
            "c:\\users\\diabo\\onedrive\\desktop\\audiotest\\plugins\\wwise\\source\\wwisesoundengine\\public\\akinclude.h",
            "c:\\users\\diabo\\onedrive\\desktop\\audiotest\\plugins\\wwise\\source\\wwisesoundengine_2022_1\\public\\wwise\\akinclude_2022_1.h",
            "c:\\users\\diabo\\onedrive\\desktop\\audiotest\\plugins\\wwise\\source\\wwisesoundengine\\public\\wwise\\presoundengineinclude.h",
            "c:\\program files\\epic games\\ue_5.1\\engine\\source\\runtime\\core\\public\\microsoft\\allowmicrosoftplatformtypes.h",
            "c:\\program files\\epic games\\ue_5.1\\engine\\source\\runtime\\core\\public\\windows\\allowwindowsplatformtypes.h",
            "c:\\program files\\epic games\\ue_5.1\\engine\\source\\runtime\\core\\public\\windows\\windowshwrapper.h",
            "c:\\program files\\epic games\\ue_5.1\\engine\\source\\runtime\\core\\public\\windows\\prewindowsapi.h",
            "c:\\program files\\epic games\\ue_5.1\\engine\\source\\runtime\\core\\public\\windows\\minwindows.h",
            "c:\\program files (x86)\\windows kits\\10\\include\\10.0.19041.0\\um\\windows.h",
            "c:\\program files (x86)\\windows kits\\10\\include\\10.0.19041.0\\shared\\sdkddkver.h",
            "c:\\program files (x86)\\microsoft visual studio\\2019\\buildtools\\vc\\tools\\msvc\\14.29.30133\\include\\excpt.h",
            "c:\\program files (x86)\\windows kits\\10\\include\\10.0.19041.0\\shared\\windef.h",
            "c:\\program files (x86)\\windows kits\\10\\include\\10.0.19041.0\\shared\\minwindef.h",
            "c:\\program files (x86)\\windows kits\\10\\include\\10.0.19041.0\\um\\winnt.h",
            "c:\\program files (x86)\\windows kits\\10\\include\\10.0.19041.0\\shared\\kernelspecs.h",
            "c:\\program files (x86)\\windows kits\\10\\include\\10.0.19041.0\\shared\\basetsd.h",
            "c:\\program files (x86)\\windows kits\\10\\include\\10.0.19041.0\\shared\\guiddef.h",
            "c:\\program files (x86)\\windows kits\\10\\include\\10.0.19041.0\\shared\\pshpack4.h",
            "c:\\program files (x86)\\windows kits\\10\\include\\10.0.19041.0\\shared\\poppack.h",
            "c:\\program files (x86)\\windows kits\\10\\include\\10.0.19041.0\\shared\\pshpack4.h",
            "c:\\program files (x86)\\windows kits\\10\\include\\10.0.19041.0\\shared\\poppack.h",
            "c:\\program files (x86)\\windows kits\\10\\include\\10.0.19041.0\\shared\\pshpack4.h",
            "c:\\program files (x86)\\windows kits\\10\\include\\10.0.19041.0\\shared\\pshpack2.h",
            "c:\\program files (x86)\\windows kits\\10\\include\\10.0.19041.0\\shared\\poppack.h",
            "c:\\program files (x86)\\windows kits\\10\\include\\10.0.19041.0\\shared\\pshpack2.h",
            "c:\\program files (x86)\\windows kits\\10\\include\\10.0.19041.0\\shared\\pshpack2.h",
            "c:\\program files (x86)\\windows kits\\10\\include\\10.0.19041.0\\shared\\poppack.h",
            "c:\\program files (x86)\\windows kits\\10\\include\\10.0.19041.0\\shared\\poppack.h",
            "c:\\program files (x86)\\windows kits\\10\\include\\10.0.19041.0\\shared\\pshpack8.h",
            "c:\\program files (x86)\\windows kits\\10\\include\\10.0.19041.0\\shared\\poppack.h",
            "c:\\program files (x86)\\windows kits\\10\\include\\10.0.19041.0\\shared\\pshpack1.h",
            "c:\\program files (x86)\\windows kits\\10\\include\\10.0.19041.0\\shared\\poppack.h",
            "c:\\program files (x86)\\windows kits\\10\\include\\10.0.19041.0\\shared\\pshpack1.h",
            "c:\\program files (x86)\\windows kits\\10\\include\\10.0.19041.0\\shared\\poppack.h",
            "c:\\program files (x86)\\windows kits\\10\\include\\10.0.19041.0\\shared\\poppack.h",
            "c:\\program files (x86)\\windows kits\\10\\include\\10.0.19041.0\\shared\\apiset.h",
            "c:\\program files (x86)\\windows kits\\10\\include\\10.0.19041.0\\shared\\ktmtypes.h",
            "c:\\program files (x86)\\windows kits\\10\\include\\10.0.19041.0\\um\\winbase.h",
            "c:\\program files (x86)\\windows kits\\10\\include\\10.0.19041.0\\shared\\apisetcconv.h",
            "c:\\program files (x86)\\windows kits\\10\\include\\10.0.19041.0\\um\\minwinbase.h",
            "c:\\program files (x86)\\windows kits\\10\\include\\10.0.19041.0\\um\\apiquery2.h",
            "c:\\program files (x86)\\windows kits\\10\\include\\10.0.19041.0\\um\\processenv.h",
            "c:\\program files (x86)\\windows kits\\10\\include\\10.0.19041.0\\um\\fileapifromapp.h",
            "c:\\program files (x86)\\windows kits\\10\\include\\10.0.19041.0\\um\\fileapi.h",
            "c:\\program files (x86)\\windows kits\\10\\include\\10.0.19041.0\\um\\debugapi.h",
            "c:\\program files (x86)\\windows kits\\10\\include\\10.0.19041.0\\um\\utilapiset.h",
            "c:\\program files (x86)\\windows kits\\10\\include\\10.0.19041.0\\um\\handleapi.h",
            "c:\\program files (x86)\\windows kits\\10\\include\\10.0.19041.0\\um\\errhandlingapi.h",
            "c:\\program files (x86)\\windows kits\\10\\include\\10.0.19041.0\\um\\fibersapi.h",
            "c:\\program files (x86)\\windows kits\\10\\include\\10.0.19041.0\\um\\namedpipeapi.h",
            "c:\\program files (x86)\\windows kits\\10\\include\\10.0.19041.0\\um\\profileapi.h",
            "c:\\program files (x86)\\windows kits\\10\\include\\10.0.19041.0\\um\\heapapi.h",
            "c:\\program files (x86)\\windows kits\\10\\include\\10.0.19041.0\\um\\ioapiset.h",
            "c:\\program files (x86)\\windows kits\\10\\include\\10.0.19041.0\\um\\synchapi.h",
            "c:\\program files (x86)\\windows kits\\10\\include\\10.0.19041.0\\um\\interlockedapi.h",
            "c:\\program files (x86)\\windows kits\\10\\include\\10.0.19041.0\\um\\processthreadsapi.h",
            "c:\\program files (x86)\\windows kits\\10\\include\\10.0.19041.0\\um\\sysinfoapi.h",
            "c:\\program files (x86)\\windows kits\\10\\include\\10.0.19041.0\\um\\memoryapi.h",
            "c:\\program files (x86)\\windows kits\\10\\include\\10.0.19041.0\\um\\enclaveapi.h",
            "c:\\program files (x86)\\windows kits\\10\\include\\10.0.19041.0\\um\\threadpoollegacyapiset.h",
            "c:\\program files (x86)\\windows kits\\10\\include\\10.0.19041.0\\um\\threadpoolapiset.h",
            "c:\\program files (x86)\\windows kits\\10\\include\\10.0.19041.0\\um\\jobapi.h",
            "c:\\program files (x86)\\windows kits\\10\\include\\10.0.19041.0\\um\\jobapi2.h",
            "c:\\program files (x86)\\windows kits\\10\\include\\10.0.19041.0\\um\\wow64apiset.h",
            "c:\\program files (x86)\\windows kits\\10\\include\\10.0.19041.0\\um\\libloaderapi.h",
            "c:\\program files (x86)\\windows kits\\10\\include\\10.0.19041.0\\um\\securitybaseapi.h",
            "c:\\program files (x86)\\windows kits\\10\\include\\10.0.19041.0\\um\\namespaceapi.h",
            "c:\\program files (x86)\\windows kits\\10\\include\\10.0.19041.0\\um\\systemtopologyapi.h",
            "c:\\program files (x86)\\windows kits\\10\\include\\10.0.19041.0\\um\\processtopologyapi.h",
            "c:\\program files (x86)\\windows kits\\10\\include\\10.0.19041.0\\um\\securityappcontainer.h",
            "c:\\program files (x86)\\windows kits\\10\\include\\10.0.19041.0\\um\\realtimeapiset.h",
            "c:\\program files (x86)\\windows kits\\10\\include\\10.0.19041.0\\shared\\winerror.h",
            "c:\\program files (x86)\\windows kits\\10\\include\\10.0.19041.0\\um\\timezoneapi.h",
            "c:\\program files (x86)\\windows kits\\10\\include\\10.0.19041.0\\um\\wingdi.h",
            "c:\\program files (x86)\\windows kits\\10\\include\\10.0.19041.0\\shared\\pshpack1.h",
            "c:\\program files (x86)\\windows kits\\10\\include\\10.0.19041.0\\shared\\poppack.h",
            "c:\\program files (x86)\\windows kits\\10\\include\\10.0.19041.0\\shared\\pshpack2.h",
            "c:\\program files (x86)\\windows kits\\10\\include\\10.0.19041.0\\shared\\poppack.h",
            "c:\\program files (x86)\\windows kits\\10\\include\\10.0.19041.0\\shared\\pshpack4.h",
            "c:\\program files (x86)\\windows kits\\10\\include\\10.0.19041.0\\shared\\poppack.h",
            "c:\\program files (x86)\\windows kits\\10\\include\\10.0.19041.0\\shared\\pshpack4.h",
            "c:\\program files (x86)\\windows kits\\10\\include\\10.0.19041.0\\shared\\poppack.h",
            "c:\\program files (x86)\\windows kits\\10\\include\\10.0.19041.0\\um\\winuser.h",
            "c:\\program files (x86)\\windows kits\\10\\include\\10.0.19041.0\\shared\\pshpack2.h",
            "c:\\program files (x86)\\windows kits\\10\\include\\10.0.19041.0\\shared\\poppack.h",
            "c:\\program files (x86)\\windows kits\\10\\include\\10.0.19041.0\\shared\\tvout.h",
            "c:\\program files (x86)\\windows kits\\10\\include\\10.0.19041.0\\um\\winnls.h",
            "c:\\program files (x86)\\windows kits\\10\\include\\10.0.19041.0\\um\\datetimeapi.h",
            "c:\\program files (x86)\\windows kits\\10\\include\\10.0.19041.0\\um\\stringapiset.h",
            "c:\\program files (x86)\\windows kits\\10\\include\\10.0.19041.0\\um\\winnls.h",
            "c:\\program files (x86)\\windows kits\\10\\include\\10.0.19041.0\\um\\wincon.h",
            "c:\\program files (x86)\\windows kits\\10\\include\\10.0.19041.0\\um\\wincontypes.h",
            "c:\\program files (x86)\\windows kits\\10\\include\\10.0.19041.0\\um\\consoleapi.h",
            "c:\\program files (x86)\\windows kits\\10\\include\\10.0.19041.0\\um\\consoleapi2.h",
            "c:\\program files (x86)\\windows kits\\10\\include\\10.0.19041.0\\um\\consoleapi3.h",
            "c:\\program files (x86)\\windows kits\\10\\include\\10.0.19041.0\\um\\winver.h",
            "c:\\program files (x86)\\windows kits\\10\\include\\10.0.19041.0\\um\\verrsrc.h",
            "c:\\program files (x86)\\windows kits\\10\\include\\10.0.19041.0\\um\\winreg.h",
            "c:\\program files (x86)\\windows kits\\10\\include\\10.0.19041.0\\um\\reason.h",
            "c:\\program files (x86)\\windows kits\\10\\include\\10.0.19041.0\\um\\winnetwk.h",
            "c:\\program files (x86)\\windows kits\\10\\include\\10.0.19041.0\\shared\\wnnc.h",
            "c:\\program files (x86)\\windows kits\\10\\include\\10.0.19041.0\\shared\\stralign.h",
            "c:\\program files (x86)\\windows kits\\10\\include\\10.0.19041.0\\um\\imm.h",
            "c:\\program files (x86)\\windows kits\\10\\include\\10.0.19041.0\\um\\ime_cmodes.h",
            "c:\\program files\\epic games\\ue_5.1\\engine\\source\\runtime\\core\\public\\windows\\postwindowsapi.h",
            "c:\\program files\\epic games\\ue_5.1\\engine\\source\\runtime\\core\\public\\microsoft\\allowmicrosoftplatformatomics.h",
            "c:\\program files\\epic games\\ue_5.1\\engine\\source\\runtime\\core\\public\\windows\\allowwindowsplatformatomics.h",
            "c:\\users\\diabo\\onedrive\\desktop\\audiotest\\plugins\\wwise\\thirdparty\\include\\ak\\akwwisesdkversion.h",
            "c:\\users\\diabo\\onedrive\\desktop\\audiotest\\plugins\\wwise\\thirdparty\\include\\ak\\soundengine\\common\\akcommondefs.h",
            "c:\\users\\diabo\\onedrive\\desktop\\audiotest\\plugins\\wwise\\thirdparty\\include\\ak\\soundengine\\common\\akspeakerconfig.h",
            "c:\\users\\diabo\\onedrive\\desktop\\audiotest\\plugins\\wwise\\thirdparty\\include\\ak\\soundengine\\common\\aktypes.h",
            "c:\\users\\diabo\\onedrive\\desktop\\audiotest\\plugins\\wwise\\thirdparty\\include\\ak\\akplatforms.h",
            "c:\\users\\diabo\\onedrive\\desktop\\audiotest\\plugins\\wwise\\thirdparty\\include\\ak\\soundengine\\platforms\\windows\\aktypes.h",
            "c:\\users\\diabo\\onedrive\\desktop\\audiotest\\plugins\\wwise\\thirdparty\\include\\ak\\soundengine\\common\\aknumeraltypes.h",
            "c:\\users\\diabo\\onedrive\\desktop\\audiotest\\plugins\\wwise\\thirdparty\\include\\ak\\soundengine\\common\\aksoundengineexport.h",
            "c:\\users\\diabo\\onedrive\\desktop\\audiotest\\plugins\\wwise\\thirdparty\\include\\ak\\soundengine\\common\\akspeakervolumes.h",
            "c:\\users\\diabo\\onedrive\\desktop\\audiotest\\plugins\\wwise\\thirdparty\\include\\ak\\soundengine\\platforms\\generic\\akspeakervolumes.h",
            "c:\\users\\diabo\\onedrive\\desktop\\audiotest\\plugins\\wwise\\thirdparty\\include\\ak\\tools\\common\\akplatformfuncs.h",
            "c:\\users\\diabo\\onedrive\\desktop\\audiotest\\plugins\\wwise\\thirdparty\\include\\ak\\soundengine\\common\\akatomic.h",
            "c:\\users\\diabo\\onedrive\\desktop\\audiotest\\plugins\\wwise\\thirdparty\\include\\ak\\soundengine\\platforms\\windows\\akatomic.h",
            "c:\\users\\diabo\\onedrive\\desktop\\audiotest\\plugins\\wwise\\thirdparty\\include\\ak\\tools\\win32\\akplatformfuncs.h",
            "c:\\users\\diabo\\onedrive\\desktop\\audiotest\\plugins\\wwise\\thirdparty\\include\\ak\\tools\\common\\akassert.h",
            "c:\\program files (x86)\\windows kits\\10\\include\\10.0.19041.0\\ucrt\\math.h",
            "c:\\users\\diabo\\onedrive\\desktop\\audiotest\\plugins\\wwise\\thirdparty\\include\\ak\\soundengine\\common\\iakpluginmemalloc.h",
            "c:\\users\\diabo\\onedrive\\desktop\\audiotest\\plugins\\wwise\\thirdparty\\include\\ak\\soundengine\\common\\akmemorymgr.h",
            "c:\\users\\diabo\\onedrive\\desktop\\audiotest\\plugins\\wwise\\thirdparty\\include\\ak\\tools\\common\\akarray.h",
            "c:\\users\\diabo\\onedrive\\desktop\\audiotest\\plugins\\wwise\\thirdparty\\include\\ak\\tools\\common\\akobject.h",
            "c:\\users\\diabo\\onedrive\\desktop\\audiotest\\plugins\\wwise\\thirdparty\\include\\ak\\tools\\common\\akstring.h",
            "c:\\users\\diabo\\onedrive\\desktop\\audiotest\\plugins\\wwise\\thirdparty\\include\\ak\\tools\\common\\akfnvhash.h",
            "c:\\users\\diabo\\onedrive\\desktop\\audiotest\\plugins\\wwise\\thirdparty\\include\\ak\\tools\\common\\akhashlist.h",
            "c:\\users\\diabo\\onedrive\\desktop\\audiotest\\plugins\\wwise\\thirdparty\\include\\ak\\tools\\common\\akkeydef.h",
            "c:\\users\\diabo\\onedrive\\desktop\\audiotest\\plugins\\wwise\\thirdparty\\include\\ak\\soundengine\\common\\aksoundengine.h",
            "c:\\users\\diabo\\onedrive\\desktop\\audiotest\\plugins\\wwise\\thirdparty\\include\\ak\\soundengine\\common\\iakplugin.h",
            "c:\\users\\diabo\\onedrive\\desktop\\audiotest\\plugins\\wwise\\thirdparty\\include\\ak\\soundengine\\common\\iakrtpcsubscriber.h",
            "c:\\users\\diabo\\onedrive\\desktop\\audiotest\\plugins\\wwise\\thirdparty\\include\\ak\\soundengine\\common\\akfputilities.h",
            "c:\\users\\diabo\\onedrive\\desktop\\audiotest\\plugins\\wwise\\thirdparty\\include\\ak\\tools\\common\\aklock.h",
            "c:\\users\\diabo\\onedrive\\desktop\\audiotest\\plugins\\wwise\\thirdparty\\include\\ak\\tools\\win32\\aklock.h",
            "c:\\users\\diabo\\onedrive\\desktop\\audiotest\\plugins\\wwise\\thirdparty\\include\\ak\\tools\\common\\akmonitorerror.h",
            "c:\\users\\diabo\\onedrive\\desktop\\audiotest\\plugins\\wwise\\thirdparty\\include\\ak\\tools\\common\\akrng.h",
            "c:\\users\\diabo\\onedrive\\desktop\\audiotest\\plugins\\wwise\\thirdparty\\include\\ak\\soundengine\\common\\iakprocessorfeatures.h",
            "c:\\users\\diabo\\onedrive\\desktop\\audiotest\\plugins\\wwise\\thirdparty\\include\\ak\\soundengine\\common\\iakplatformcontext.h",
            "c:\\users\\diabo\\onedrive\\desktop\\audiotest\\plugins\\wwise\\thirdparty\\include\\ak\\soundengine\\common\\akmiditypes.h",
            "c:\\users\\diabo\\onedrive\\desktop\\audiotest\\plugins\\wwise\\thirdparty\\include\\ak\\soundengine\\common\\akcallback.h",
            "c:\\program files (x86)\\windows kits\\10\\include\\10.0.19041.0\\ucrt\\math.h",
            "c:\\users\\diabo\\onedrive\\desktop\\audiotest\\plugins\\wwise\\thirdparty\\include\\ak\\soundengine\\platforms\\windows\\akwinsoundengine.h",
            "c:\\users\\diabo\\onedrive\\desktop\\audiotest\\plugins\\wwise\\thirdparty\\include\\ak\\soundengine\\platforms\\windows\\akplatformcontext.h",
            "c:\\users\\diabo\\onedrive\\desktop\\audiotest\\plugins\\wwise\\thirdparty\\include\\ak\\spatialaudio\\common\\akspatialaudio.h",
            "c:\\users\\diabo\\onedrive\\desktop\\audiotest\\plugins\\wwise\\thirdparty\\include\\ak\\spatialaudio\\common\\akspatialaudiotypes.h",
            "c:\\users\\diabo\\onedrive\\desktop\\audiotest\\plugins\\wwise\\thirdparty\\include\\ak\\plugin\\akreflectgamedata.h",
            "c:\\users\\diabo\\onedrive\\desktop\\audiotest\\plugins\\wwise\\thirdparty\\include\\ak\\ibytes.h",
            "c:\\users\\diabo\\onedrive\\desktop\\audiotest\\plugins\\wwise\\thirdparty\\include\\ak\\soundengine\\common\\akvirtualacoustics.h",
            "c:\\users\\diabo\\onedrive\\desktop\\audiotest\\plugins\\wwise\\thirdparty\\include\\ak\\soundengine\\common\\akmodule.h",
            "c:\\users\\diabo\\onedrive\\desktop\\audiotest\\plugins\\wwise\\thirdparty\\include\\ak\\soundengine\\common\\iakstreammgr.h",
            "c:\\users\\diabo\\onedrive\\desktop\\audiotest\\plugins\\wwise\\thirdparty\\include\\ak\\soundengine\\common\\akstreammgrmodule.h",
            "c:\\users\\diabo\\onedrive\\desktop\\audiotest\\plugins\\wwise\\thirdparty\\include\\ak\\tools\\common\\akinstrument.h",
            "c:\\users\\diabo\\onedrive\\desktop\\audiotest\\plugins\\wwise\\thirdparty\\include\\ak\\tools\\common\\akprofilingid.h",
            "c:\\users\\diabo\\onedrive\\desktop\\audiotest\\plugins\\wwise\\thirdparty\\include\\ak\\musicengine\\common\\akmusicengine.h",
            "c:\\users\\diabo\\onedrive\\desktop\\audiotest\\plugins\\wwise\\thirdparty\\include\\ak\\comm\\akcommunication.h",
            "c:\\users\\diabo\\onedrive\\desktop\\audiotest\\plugins\\wwise\\thirdparty\\include\\ak\\plugin\\akaudioinputplugin.h",
            "c:\\users\\diabo\\onedrive\\desktop\\audiotest\\plugins\\wwise\\thirdparty\\include\\ak\\soundengine\\common\\akqueryparameters.h",
            "c:\\users\\diabo\\onedrive\\desktop\\audiotest\\plugins\\wwise\\thirdparty\\include\\ak\\wwiseauthoringapi\\akautobahn\\client.h",
            "c:\\users\\diabo\\onedrive\\desktop\\audiotest\\plugins\\wwise\\thirdparty\\include\\ak\\wwiseauthoringapi\\akautobahn\\autobahn.h",
            "c:\\program files (x86)\\microsoft visual studio\\2019\\buildtools\\vc\\tools\\msvc\\14.29.30133\\include\\condition_variable",
            "c:\\program files (x86)\\microsoft visual studio\\2019\\buildtools\\vc\\tools\\msvc\\14.29.30133\\include\\__msvc_chrono.hpp",
            "c:\\program files (x86)\\microsoft visual studio\\2019\\buildtools\\vc\\tools\\msvc\\14.29.30133\\include\\ratio",
            "c:\\program files (x86)\\microsoft visual studio\\2019\\buildtools\\vc\\tools\\msvc\\14.29.30133\\include\\mutex",
            "c:\\program files (x86)\\microsoft visual studio\\2019\\buildtools\\vc\\tools\\msvc\\14.29.30133\\include\\thread",
            "c:\\program files (x86)\\windows kits\\10\\include\\10.0.19041.0\\ucrt\\process.h",
            "c:\\program files (x86)\\windows kits\\10\\include\\10.0.19041.0\\ucrt\\corecrt_startup.h",
            "c:\\program files (x86)\\windows kits\\10\\include\\10.0.19041.0\\ucrt\\math.h",
            "c:\\program files (x86)\\microsoft visual studio\\2019\\buildtools\\vc\\tools\\msvc\\14.29.30133\\include\\vcruntime_startup.h",
            "c:\\program files (x86)\\microsoft visual studio\\2019\\buildtools\\vc\\tools\\msvc\\14.29.30133\\include\\future",
            "c:\\program files (x86)\\microsoft visual studio\\2019\\buildtools\\vc\\tools\\msvc\\14.29.30133\\include\\ppltasks.h",
            "c:\\program files (x86)\\microsoft visual studio\\2019\\buildtools\\vc\\tools\\msvc\\14.29.30133\\include\\pplwin.h",
            "c:\\program files (x86)\\microsoft visual studio\\2019\\buildtools\\vc\\tools\\msvc\\14.29.30133\\include\\pplinterface.h",
            "c:\\program files (x86)\\microsoft visual studio\\2019\\buildtools\\vc\\tools\\msvc\\14.29.30133\\include\\ppltaskscheduler.h",
            "c:\\program files (x86)\\microsoft visual studio\\2019\\buildtools\\vc\\tools\\msvc\\14.29.30133\\include\\crtdefs.h",
            "c:\\program files (x86)\\microsoft visual studio\\2019\\buildtools\\vc\\tools\\msvc\\14.29.30133\\include\\pplcancellation_token.h",
            "c:\\program files (x86)\\microsoft visual studio\\2019\\buildtools\\vc\\tools\\msvc\\14.29.30133\\include\\map",
            "c:\\program files (x86)\\microsoft visual studio\\2019\\buildtools\\vc\\tools\\msvc\\14.29.30133\\include\\xtree",
            "c:\\program files (x86)\\microsoft visual studio\\2019\\buildtools\\vc\\tools\\msvc\\14.29.30133\\include\\queue",
            "c:\\program files (x86)\\microsoft visual studio\\2019\\buildtools\\vc\\tools\\msvc\\14.29.30133\\include\\deque",
            "c:\\program files (x86)\\microsoft visual studio\\2019\\buildtools\\vc\\tools\\msvc\\14.29.30133\\include\\string",
            "c:\\users\\diabo\\onedrive\\desktop\\audiotest\\plugins\\wwise\\thirdparty\\include\\ak\\wwiseauthoringapi\\akautobahn\\akvariant.h",
            "c:\\users\\diabo\\onedrive\\desktop\\audiotest\\plugins\\wwise\\thirdparty\\include\\ak\\wwiseauthoringapi\\akvariantbase.h",
            "c:\\program files (x86)\\microsoft visual studio\\2019\\buildtools\\vc\\tools\\msvc\\14.29.30133\\include\\string_view",
            "c:\\users\\diabo\\onedrive\\desktop\\audiotest\\plugins\\wwise\\thirdparty\\include\\ak\\wwiseauthoringapi\\akguid.h",
            "c:\\users\\diabo\\onedrive\\desktop\\audiotest\\plugins\\wwise\\thirdparty\\include\\ak\\wwiseauthoringapi\\akautobahn\\akjson.h",
            "c:\\users\\diabo\\onedrive\\desktop\\audiotest\\plugins\\wwise\\thirdparty\\include\\ak\\wwiseauthoringapi\\akjsonbase.h",
            "c:\\users\\diabo\\onedrive\\desktop\\audiotest\\plugins\\wwise\\thirdparty\\include\\ak\\wwiseauthoringapi\\akautobahn\\jsonprovider.h",
            "c:\\users\\diabo\\onedrive\\desktop\\audiotest\\plugins\\wwise\\thirdparty\\include\\ak\\wwiseauthoringapi\\akautobahn\\iwebsocketclienthandler.h",
            "c:\\users\\diabo\\onedrive\\desktop\\audiotest\\plugins\\wwise\\thirdparty\\include\\ak\\wwiseauthoringapi\\akautobahn\\websocketclient.h",
            "c:\\users\\diabo\\onedrive\\desktop\\audiotest\\plugins\\wwise\\thirdparty\\include\\ak\\wwiseauthoringapi\\akautobahn\\futureutils.h",
            "c:\\users\\diabo\\onedrive\\desktop\\audiotest\\plugins\\wwise\\thirdparty\\include\\ak\\wwiseauthoringapi\\waapi.h",
            "c:\\users\\diabo\\onedrive\\desktop\\audiotest\\plugins\\wwise\\source\\wwisesoundengine\\public\\wwise\\postsoundengineinclude.h",
            "c:\\program files\\epic games\\ue_5.1\\engine\\source\\runtime\\core\\public\\microsoft\\hidemicrosoftplatformtypes.h",
            "c:\\program files\\epic games\\ue_5.1\\engine\\source\\runtime\\core\\public\\windows\\hidewindowsplatformtypes.h",
            "c:\\program files\\epic games\\ue_5.1\\engine\\source\\runtime\\core\\public\\microsoft\\hidemicrosoftplatformatomics.h",
            "c:\\program files\\epic games\\ue_5.1\\engine\\source\\runtime\\core\\public\\windows\\hidewindowsplatformatomics.h",
            "c:\\users\\diabo\\onedrive\\desktop\\audiotest\\plugins\\wwise\\source\\akaudio\\classes\\platforms\\akplatform_windows\\akwindowsplatform.h",
            "c:\\users\\diabo\\onedrive\\desktop\\audiotest\\plugins\\wwise\\source\\akaudio\\classes\\platforms\\akplatformbase.h",
            "c:\\users\\diabo\\onedrive\\desktop\\audiotest\\plugins\\wwise\\source\\akaudio\\classes\\platforms\\akplatform_windows\\akwindowsinitializationsettings.h",
            "c:\\users\\diabo\\onedrive\\desktop\\audiotest\\plugins\\wwise\\source\\akaudio\\classes\\initializationsettings\\akinitializationsettings.h",
            "c:\\users\\diabo\\onedrive\\desktop\\audiotest\\plugins\\wwise\\intermediate\\build\\win64\\unrealgame\\inc\\akaudio\\uht\\akinitializationsettings.generated.h",
            "c:\\users\\diabo\\onedrive\\desktop\\audiotest\\plugins\\wwise\\source\\akaudio\\classes\\initializationsettings\\akplatforminitialisationsettingsbase.h",
            "c:\\users\\diabo\\onedrive\\desktop\\audiotest\\plugins\\wwise\\intermediate\\build\\win64\\unrealgame\\inc\\akaudio\\uht\\akplatforminitialisationsettingsbase.generated.h",
            "c:\\users\\diabo\\onedrive\\desktop\\audiotest\\plugins\\wwise\\intermediate\\build\\win64\\unrealgame\\inc\\akaudio\\uht\\akwindowsinitializationsettings.generated.h",
            "c:\\program files\\epic games\\ue_5.1\\engine\\source\\runtime\\engine\\public\\latentactions.h",
            "c:\\users\\diabo\\onedrive\\desktop\\audiotest\\plugins\\wwise\\source\\akaudio\\classes\\akdeprecated.h",
            "c:\\users\\diabo\\onedrive\\desktop\\audiotest\\plugins\\wwise\\source\\akaudio\\classes\\akaudiotype.h",
            "c:\\users\\diabo\\onedrive\\desktop\\audiotest\\plugins\\wwise\\source\\wwiseresourceloader\\public\\wwise\\info\\wwiseobjectinfo.h",
            "c:\\users\\diabo\\onedrive\\desktop\\audiotest\\plugins\\wwise\\intermediate\\build\\win64\\unrealgame\\inc\\wwiseresourceloader\\uht\\wwiseobjectinfo.generated.h",
            "c:\\users\\diabo\\onedrive\\desktop\\audiotest\\plugins\\wwise\\intermediate\\build\\win64\\unrealgame\\inc\\akaudio\\uht\\akaudiotype.generated.h",
            "c:\\users\\diabo\\onedrive\\desktop\\audiotest\\plugins\\wwise\\intermediate\\build\\win64\\unrealgame\\inc\\akaudio\\uht\\akdeprecated.generated.h",
            "c:\\users\\diabo\\onedrive\\desktop\\audiotest\\plugins\\wwise\\intermediate\\build\\win64\\unrealgame\\inc\\akaudio\\uht\\akgameplaytypes.generated.h",
            "c:\\users\\diabo\\onedrive\\desktop\\audiotest\\plugins\\wwise\\intermediate\\build\\win64\\unrealgame\\inc\\akaudio\\uht\\akgeometrycomponent.gen.cpp",
            "c:\\users\\diabo\\onedrive\\desktop\\audiotest\\plugins\\wwise\\source\\akaudio\\classes\\akgeometrycomponent.h",
            "c:\\users\\diabo\\onedrive\\desktop\\audiotest\\plugins\\wwise\\source\\akaudio\\classes\\akacoustictexture.h",
            "c:\\users\\diabo\\onedrive\\desktop\\audiotest\\plugins\\wwise\\source\\wwiseresourceloader\\public\\wwise\\cookeddata\\wwiseacoustictexturecookeddata.h",
            "c:\\users\\diabo\\onedrive\\desktop\\audiotest\\plugins\\wwise\\intermediate\\build\\win64\\unrealgame\\inc\\wwiseresourceloader\\uht\\wwiseacoustictexturecookeddata.generated.h",
            "c:\\users\\diabo\\onedrive\\desktop\\audiotest\\plugins\\wwise\\intermediate\\build\\win64\\unrealgame\\inc\\akaudio\\uht\\akacoustictexture.generated.h",
            "c:\\program files\\epic games\\ue_5.1\\engine\\source\\runtime\\physicscore\\public\\physicalmaterials\\physicalmaterial.h",
            "c:\\program files\\epic games\\ue_5.1\\engine\\source\\runtime\\physicscore\\public\\physicssettingsenums.h",
            "c:\\program files\\epic games\\ue_5.1\\engine\\intermediate\\build\\win64\\unrealgame\\inc\\physicscore\\uht\\physicssettingsenums.generated.h",
            "c:\\program files\\epic games\\ue_5.1\\engine\\intermediate\\build\\win64\\unrealgame\\inc\\physicscore\\uht\\physicalmaterial.generated.h",
            "c:\\users\\diabo\\onedrive\\desktop\\audiotest\\plugins\\wwise\\source\\akaudio\\classes\\akacoustictexturesetcomponent.h",
            "c:\\users\\diabo\\onedrive\\desktop\\audiotest\\plugins\\wwise\\source\\akaudio\\classes\\aksettings.h",
            "c:\\program files\\epic games\\ue_5.1\\engine\\source\\runtime\\assetregistry\\public\\assetregistry\\assetregistrymodule.h",
            "c:\\program files\\epic games\\ue_5.1\\engine\\source\\runtime\\assetregistry\\public\\assetregistry\\iassetregistry.h",
            "c:\\program files\\epic games\\ue_5.1\\engine\\source\\runtime\\coreuobject\\public\\assetregistry\\arfilter.h",
            "c:\\program files\\epic games\\ue_5.1\\engine\\source\\runtime\\coreuobject\\public\\misc\\assetregistryinterface.h",
            "c:\\program files\\epic games\\ue_5.1\\engine\\intermediate\\build\\win64\\unrealgame\\inc\\assetregistry\\uht\\iassetregistry.generated.h",
            "c:\\users\\diabo\\onedrive\\desktop\\audiotest\\plugins\\wwise\\source\\wwisesoundengine\\public\\akuefeatures.h",
            "c:\\users\\diabo\\onedrive\\desktop\\audiotest\\plugins\\wwise\\source\\akaudio\\classes\\akrtpc.h",
            "c:\\users\\diabo\\onedrive\\desktop\\audiotest\\plugins\\wwise\\source\\wwiseresourceloader\\public\\wwise\\cookeddata\\wwisegameparametercookeddata.h",
            "c:\\users\\diabo\\onedrive\\desktop\\audiotest\\plugins\\wwise\\intermediate\\build\\win64\\unrealgame\\inc\\wwiseresourceloader\\uht\\wwisegameparametercookeddata.generated.h",
            "c:\\users\\diabo\\onedrive\\desktop\\audiotest\\plugins\\wwise\\intermediate\\build\\win64\\unrealgame\\inc\\akaudio\\uht\\akrtpc.generated.h",
            "c:\\users\\diabo\\onedrive\\desktop\\audiotest\\plugins\\wwise\\intermediate\\build\\win64\\unrealgame\\inc\\akaudio\\uht\\aksettings.generated.h",
            "c:\\users\\diabo\\onedrive\\desktop\\audiotest\\plugins\\wwise\\intermediate\\build\\win64\\unrealgame\\inc\\akaudio\\uht\\akacoustictexturesetcomponent.generated.h",
            "c:\\users\\diabo\\onedrive\\desktop\\audiotest\\plugins\\wwise\\source\\akaudio\\classes\\akgeometrydata.h",
            "c:\\users\\diabo\\onedrive\\desktop\\audiotest\\plugins\\wwise\\intermediate\\build\\win64\\unrealgame\\inc\\akaudio\\uht\\akgeometrydata.generated.h",
            "c:\\users\\diabo\\onedrive\\desktop\\audiotest\\plugins\\wwise\\intermediate\\build\\win64\\unrealgame\\inc\\akaudio\\uht\\akgeometrycomponent.generated.h",
            "c:\\program files\\epic games\\ue_5.1\\engine\\source\\runtime\\coreuobject\\public\\serialization\\archiveuobjectfromstructuredarchive.h",
            "c:\\users\\diabo\\onedrive\\desktop\\audiotest\\plugins\\wwise\\intermediate\\build\\win64\\unrealgame\\inc\\akaudio\\uht\\akgeometrydata.gen.cpp",
            "c:\\users\\diabo\\onedrive\\desktop\\audiotest\\plugins\\wwise\\intermediate\\build\\win64\\unrealgame\\inc\\akaudio\\uht\\akgroupvalue.gen.cpp",
            "c:\\users\\diabo\\onedrive\\desktop\\audiotest\\plugins\\wwise\\source\\akaudio\\classes\\akgroupvalue.h",
            "c:\\users\\diabo\\onedrive\\desktop\\audiotest\\plugins\\wwise\\source\\wwiseresourceloader\\public\\wwise\\cookeddata\\wwisegroupvaluecookeddata.h",
            "c:\\users\\diabo\\onedrive\\desktop\\audiotest\\plugins\\wwise\\intermediate\\build\\win64\\unrealgame\\inc\\wwiseresourceloader\\uht\\wwisegroupvaluecookeddata.generated.h",
            "c:\\users\\diabo\\onedrive\\desktop\\audiotest\\plugins\\wwise\\source\\wwiseresourceloader\\public\\wwise\\loaded\\wwiseloadedgroupvalue.h",
            "c:\\users\\diabo\\onedrive\\desktop\\audiotest\\plugins\\wwise\\source\\wwiseresourceloader\\public\\wwise\\info\\wwisegroupvalueinfo.h",
            "c:\\users\\diabo\\onedrive\\desktop\\audiotest\\plugins\\wwise\\intermediate\\build\\win64\\unrealgame\\inc\\wwiseresourceloader\\uht\\wwisegroupvalueinfo.generated.h",
            "c:\\users\\diabo\\onedrive\\desktop\\audiotest\\plugins\\wwise\\intermediate\\build\\win64\\unrealgame\\inc\\akaudio\\uht\\akgroupvalue.generated.h",
            "c:\\users\\diabo\\onedrive\\desktop\\audiotest\\plugins\\wwise\\intermediate\\build\\win64\\unrealgame\\inc\\akaudio\\uht\\akhololensinitializationsettings.gen.cpp",
            "c:\\users\\diabo\\onedrive\\desktop\\audiotest\\plugins\\wwise\\source\\akaudio\\classes\\platforms\\akplatform_hololens\\akhololensinitializationsettings.h",
            "c:\\users\\diabo\\onedrive\\desktop\\audiotest\\plugins\\wwise\\intermediate\\build\\win64\\unrealgame\\inc\\akaudio\\uht\\akhololensinitializationsettings.generated.h",
            "c:\\users\\diabo\\onedrive\\desktop\\audiotest\\plugins\\wwise\\intermediate\\build\\win64\\unrealgame\\inc\\akaudio\\uht\\akhololensplatforminfo.gen.cpp",
            "c:\\users\\diabo\\onedrive\\desktop\\audiotest\\plugins\\wwise\\source\\akaudio\\classes\\platforms\\akplatform_hololens\\akhololensplatforminfo.h",
            "c:\\users\\diabo\\onedrive\\desktop\\audiotest\\plugins\\wwise\\source\\akaudio\\classes\\platforms\\akplatforminfo.h",
            "c:\\program files\\epic games\\ue_5.1\\engine\\source\\runtime\\engine\\classes\\engine\\gameengine.h",
            "c:\\program files\\epic games\\ue_5.1\\engine\\source\\runtime\\slate\\public\\widgets\\sviewport.h",
            "c:\\program files\\epic games\\ue_5.1\\engine\\source\\runtime\\moviescenecapture\\public\\moviescenecapturehandle.h",
            "c:\\program files\\epic games\\ue_5.1\\engine\\intermediate\\build\\win64\\unrealgame\\inc\\engine\\uht\\gameengine.generated.h",
            "c:\\users\\diabo\\onedrive\\desktop\\audiotest\\plugins\\wwise\\source\\akaudio\\public\\akaudiodevice.h",
            "c:\\users\\diabo\\onedrive\\desktop\\audiotest\\plugins\\wwise\\source\\akaudio\\classes\\akenvironmentindex.h",
            "c:\\users\\diabo\\onedrive\\desktop\\audiotest\\plugins\\wwise\\source\\akaudio\\classes\\akjobworkerscheduler.h",
            "c:\\users\\diabo\\onedrive\\desktop\\audiotest\\plugins\\wwise\\source\\wwiseresourceloader\\public\\wwise\\wwisesharedlanguageid.h",
            "c:\\users\\diabo\\onedrive\\desktop\\audiotest\\plugins\\wwise\\source\\wwiseresourceloader\\public\\wwise\\wwiselanguageid.h",
            "c:\\users\\diabo\\onedrive\\desktop\\audiotest\\plugins\\wwise\\intermediate\\build\\win64\\unrealgame\\inc\\wwiseresourceloader\\uht\\wwiselanguageid.generated.h",
            "c:\\users\\diabo\\onedrive\\desktop\\audiotest\\plugins\\wwise\\source\\wwisefilehandler\\public\\wwise\\cookeddata\\wwiselanguagecookeddata.h",
            "c:\\users\\diabo\\onedrive\\desktop\\audiotest\\plugins\\wwise\\intermediate\\build\\win64\\unrealgame\\inc\\wwisefilehandler\\uht\\wwiselanguagecookeddata.generated.h",
            "c:\\users\\diabo\\onedrive\\desktop\\audiotest\\plugins\\wwise\\intermediate\\build\\win64\\unrealgame\\inc\\wwiseresourceloader\\uht\\wwisesharedlanguageid.generated.h",
            "c:\\users\\diabo\\onedrive\\desktop\\audiotest\\plugins\\wwise\\source\\akaudio\\public\\wwise\\stats\\akaudio.h",
            "c:\\users\\diabo\\onedrive\\desktop\\audiotest\\plugins\\wwise\\intermediate\\build\\win64\\unrealgame\\inc\\akaudio\\uht\\akplatforminfo.generated.h",
            "c:\\users\\diabo\\onedrive\\desktop\\audiotest\\plugins\\wwise\\intermediate\\build\\win64\\unrealgame\\inc\\akaudio\\uht\\akhololensplatforminfo.generated.h",
            "c:\\users\\diabo\\onedrive\\desktop\\audiotest\\plugins\\wwise\\intermediate\\build\\win64\\unrealgame\\inc\\akaudio\\uht\\akinitbank.gen.cpp",
            "c:\\users\\diabo\\onedrive\\desktop\\audiotest\\plugins\\wwise\\source\\akaudio\\classes\\akinitbank.h",
            "c:\\users\\diabo\\onedrive\\desktop\\audiotest\\plugins\\wwise\\source\\wwiseresourceloader\\public\\wwise\\cookeddata\\wwiseinitbankcookeddata.h",
            "c:\\users\\diabo\\onedrive\\desktop\\audiotest\\plugins\\wwise\\source\\wwisefilehandler\\public\\wwise\\cookeddata\\wwisesoundbankcookeddata.h",
            "c:\\users\\diabo\\onedrive\\desktop\\audiotest\\plugins\\wwise\\intermediate\\build\\win64\\unrealgame\\inc\\wwisefilehandler\\uht\\wwisesoundbankcookeddata.generated.h",
            "c:\\users\\diabo\\onedrive\\desktop\\audiotest\\plugins\\wwise\\source\\wwisefilehandler\\public\\wwise\\cookeddata\\wwisemediacookeddata.h",
            "c:\\users\\diabo\\onedrive\\desktop\\audiotest\\plugins\\wwise\\intermediate\\build\\win64\\unrealgame\\inc\\wwisefilehandler\\uht\\wwisemediacookeddata.generated.h",
            "c:\\users\\diabo\\onedrive\\desktop\\audiotest\\plugins\\wwise\\intermediate\\build\\win64\\unrealgame\\inc\\wwiseresourceloader\\uht\\wwiseinitbankcookeddata.generated.h",
            "c:\\users\\diabo\\onedrive\\desktop\\audiotest\\plugins\\wwise\\source\\wwiseresourceloader\\public\\wwise\\loaded\\wwiseloadedinitbank.h",
            "c:\\users\\diabo\\onedrive\\desktop\\audiotest\\plugins\\wwise\\intermediate\\build\\win64\\unrealgame\\inc\\akaudio\\uht\\akinitbank.generated.h",
            "c:\\users\\diabo\\onedrive\\desktop\\audiotest\\plugins\\wwise\\intermediate\\build\\win64\\unrealgame\\inc\\akaudio\\uht\\akinitializationsettings.gen.cpp"
        ],
        "ImportedModules": [],
        "ImportedHeaderUnits": []
    }
}